Workbook

Sheet Summary
A2: 28 Athabaska Avenue
A3: Common Ground Initiative · development model · illustrative
B4: 516 units · 43 storeys · North York, Toronto
A6: HEADLINE METRICS
B7: Total development cost | C7: =Assumptions!$C$17 | E7: Stabilized NOI | F7: =(((((ROUND(Assumptions!$C$5*Assumptions!$C$10,0)*(Assumptions!$C$9*Assumptions!$C$11)+(Assumptions!$C$5-ROUND(Assumptions!$C$5*Assumptions!$C$10,0))*Assumptions!$C$9)*12)+Assumptions!$C$12)*(1-Assumptions!$C$13))-Assumptions!$C$14)
B8: DSCR | C8: =(((((ROUND(Assumptions!$C$5*Assumptions!$C$10,0)*(Assumptions!$C$9*Assumptions!$C$11)+(Assumptions!$C$5-ROUND(Assumptions!$C$5*Assumptions!$C$10,0))*Assumptions!$C$9)*12)+Assumptions!$C$12)*(1-Assumptions!$C$13))-Assumptions!$C$14)/(-PMT(Assumptions!$C$18/12,Assumptions!$C$19*12,(Assumptions!$C$17*Assumptions!$C$22))*12) | E8: Loan-to-cost | F8: =(Assumptions!$C$17*Assumptions!$C$22)/Assumptions!$C$17
B9: CMHC mortgage | C9: =(Assumptions!$C$17*Assumptions!$C$22) | E9: Forgivable (BCH) loan | F9: =Assumptions!$C$17*Assumptions!$C$21
A11: WHAT EACH PARTY GETS
A12: Party | B12: Puts in | C12: Gets out (20-yr)
B13: Landowner | C13: The land (lease) | E13: =Returns!$C$8
B14: Non-profit operator | C14: $0 capital | E14: =Returns!$C$16
B15: Governments | C15: 45% forgivable+municipal | E15: Housing + fiscal return
B16: Residents | C16: — | E16: 155 homes at 80% MMR
B18: Ubuntu Land Trust & Developments · “I am because we are”

Sheet Assumptions
A2: Assumptions
A3: Edit these inputs — every other tab recalculates
A4: PROGRAM
B5: Total units | C5: 516 | D5: From SPA/ZBA architectural set
B6: Buildable GFA (sf) | C6: 410000 | D6: Estimate — confirm with architect
B7: Land value ($/buildable sf) | C7: 100 | D7: Fully-approved North York comp
A8: RENTS & AFFORDABILITY
B9: Median market rent ($/mo) | C9: 2550 | D9: Blended market rent, all unit types
B10: Affordable share of units | C10: 0.3 | D10: CMHC MLI Select affordability tier
B11: Affordable rent (% of MMR) | C11: 0.8 | D11: 80% of median market rent
B12: Ancillary income ($/yr) | C12: 459200 | D12: Parking, lockers, other
B13: Vacancy & credit loss | C13: 0.03
B14: Operating expenses ($/yr) | C14: 5808000 | D14: ~39% of EGI
B15: NOI growth (annual) | C15: 0.0275 | D15: Rent/expense escalation
A16: FINANCING
B17: Total development cost | C17: 328000000 | D17: ~$636k/unit incl. land
B18: Mortgage rate | C18: 0.0425 | D18: CMHC MLI Select, illustrative
B19: Amortization (years) | C19: 50 | D19: MLI Select up to 50 yr
B20: Cap rate | C20: 0.0425 | D20: For stabilized value
B21: Capital stack — BCH (forgivable) | C21: 0.4 | D21: No payments
B22: Capital stack — CMHC MLI Select | C22: 0.5 | D22: The mortgage
B23: Capital stack — City of Toronto | C23: 0.05 | D23: Municipal contribution
B24: Capital stack — Landowner equity | C24: 0.05 | D24: Retained land
A25: DEAL TERMS
B26: Day-1 land draw (% of land value) | C26: 0.6 | D26: Cash to landowner at close
B27: Landowner cash-flow share | C27: 0.6 | D27: Of net cash flow after debt
B28: NFP cash-flow share | C28: 0.4
B29: Selling cost (if sold today) | C29: 0.05

Sheet Sources & Uses
A2: Sources & Uses
A3: Total development cost and how it is funded
A4: USES OF FUNDS
A5: Use | B5: Amount | C5: % of TDC
B6: Land (full value) | C6: =(Assumptions!$C$6*Assumptions!$C$7) | D6: =C6/Assumptions!$C$17
B7: Hard construction | C7: 186000000 | D7: =C7/Assumptions!$C$17
B8: Soft costs | C8: 60000000 | D8: =C8/Assumptions!$C$17
B9: Construction financing | C9: 26000000 | D9: =C9/Assumptions!$C$17
B10: Contingency | C10: 15000000 | D10: =C10/Assumptions!$C$17
B11: Total development cost | C11: =SUM(C6:C10) | D11: =C11/Assumptions!$C$17
B12: per unit | C12: =C11/Assumptions!$C$5
A14: SOURCES OF FUNDS
A15: Source | B15: Amount | C15: % of TDC
B16: Build Canada Homes (forgivable) | C16: =Assumptions!$C$17*Assumptions!$C$21 | D16: =Assumptions!$C$21
B17: CMHC MLI Select mortgage | C17: =Assumptions!$C$17*Assumptions!$C$22 | D17: =Assumptions!$C$22
B18: City of Toronto | C18: =Assumptions!$C$17*Assumptions!$C$23 | D18: =Assumptions!$C$23
B19: Landowner equity (land) | C19: =Assumptions!$C$17*Assumptions!$C$24 | D19: =Assumptions!$C$24
B20: Total sources | C20: =SUM(C16:C19) | D20: =SUM(D16:D19)

Sheet Operating
A2: Stabilized Operating Pro Forma
A3: Year-1 stabilized · 30% of units at 80% of median market rent
A4: Line | B4: Basis | C4: Annual
B5: Market rent revenue | C5: =(Assumptions!$C$5-ROUND(Assumptions!$C$5*Assumptions!$C$10,0)) units × MMR × 12 | D5: =(Assumptions!$C$5-ROUND(Assumptions!$C$5*Assumptions!$C$10,0))*Assumptions!$C$9*12
B6: Affordable rent revenue | C6: =ROUND(Assumptions!$C$5*Assumptions!$C$10,0) units × 80% MMR × 12 | D6: =ROUND(Assumptions!$C$5*Assumptions!$C$10,0)*(Assumptions!$C$9*Assumptions!$C$11)*12
B7: Ancillary income | C7: parking/lockers/other | D7: =Assumptions!$C$12
B8: Gross potential income | D8: =(((ROUND(Assumptions!$C$5*Assumptions!$C$10,0)*(Assumptions!$C$9*Assumptions!$C$11)+(Assumptions!$C$5-ROUND(Assumptions!$C$5*Assumptions!$C$10,0))*Assumptions!$C$9)*12)+Assumptions!$C$12)
B9: Vacancy & credit loss | D9: =-(((ROUND(Assumptions!$C$5*Assumptions!$C$10,0)*(Assumptions!$C$9*Assumptions!$C$11)+(Assumptions!$C$5-ROUND(Assumptions!$C$5*Assumptions!$C$10,0))*Assumptions!$C$9)*12)+Assumptions!$C$12)*Assumptions!$C$13
B10: Effective gross income | D10: =((((ROUND(Assumptions!$C$5*Assumptions!$C$10,0)*(Assumptions!$C$9*Assumptions!$C$11)+(Assumptions!$C$5-ROUND(Assumptions!$C$5*Assumptions!$C$10,0))*Assumptions!$C$9)*12)+Assumptions!$C$12)*(1-Assumptions!$C$13))
B11: Operating expenses | C11: ~39% of EGI | D11: =-Assumptions!$C$14
B12: Net operating income | D12: =(((((ROUND(Assumptions!$C$5*Assumptions!$C$10,0)*(Assumptions!$C$9*Assumptions!$C$11)+(Assumptions!$C$5-ROUND(Assumptions!$C$5*Assumptions!$C$10,0))*Assumptions!$C$9)*12)+Assumptions!$C$12)*(1-Assumptions!$C$13))-Assumptions!$C$14)
A14: COVERAGE
A15: Metric | C15: Value
B16: Mortgage (CMHC, 50% of TDC) | D16: =(Assumptions!$C$17*Assumptions!$C$22)
B17: Annual debt service | D17: =(-PMT(Assumptions!$C$18/12,Assumptions!$C$19*12,(Assumptions!$C$17*Assumptions!$C$22))*12)
B18: DSCR | D18: =(((((ROUND(Assumptions!$C$5*Assumptions!$C$10,0)*(Assumptions!$C$9*Assumptions!$C$11)+(Assumptions!$C$5-ROUND(Assumptions!$C$5*Assumptions!$C$10,0))*Assumptions!$C$9)*12)+Assumptions!$C$12)*(1-Assumptions!$C$13))-Assumptions!$C$14)/(-PMT(Assumptions!$C$18/12,Assumptions!$C$19*12,(Assumptions!$C$17*Assumptions!$C$22))*12)
B19: Net cash flow after debt | D19: =(((((ROUND(Assumptions!$C$5*Assumptions!$C$10,0)*(Assumptions!$C$9*Assumptions!$C$11)+(Assumptions!$C$5-ROUND(Assumptions!$C$5*Assumptions!$C$10,0))*Assumptions!$C$9)*12)+Assumptions!$C$12)*(1-Assumptions!$C$13))-Assumptions!$C$14)-(-PMT(Assumptions!$C$18/12,Assumptions!$C$19*12,(Assumptions!$C$17*Assumptions!$C$22))*12)
B20: Stabilized value (cap rate) | D20: =(((((ROUND(Assumptions!$C$5*Assumptions!$C$10,0)*(Assumptions!$C$9*Assumptions!$C$11)+(Assumptions!$C$5-ROUND(Assumptions!$C$5*Assumptions!$C$10,0))*Assumptions!$C$9)*12)+Assumptions!$C$12)*(1-Assumptions!$C$13))-Assumptions!$C$14)/Assumptions!$C$20
B21: Loan-to-value | D21: =(Assumptions!$C$17*Assumptions!$C$22)/((((((ROUND(Assumptions!$C$5*Assumptions!$C$10,0)*(Assumptions!$C$9*Assumptions!$C$11)+(Assumptions!$C$5-ROUND(Assumptions!$C$5*Assumptions!$C$10,0))*Assumptions!$C$9)*12)+Assumptions!$C$12)*(1-Assumptions!$C$13))-Assumptions!$C$14)/Assumptions!$C$20)
B22: Break-even occupancy | D22: =(Assumptions!$C$14+(-PMT(Assumptions!$C$18/12,Assumptions!$C$19*12,(Assumptions!$C$17*Assumptions!$C$22))*12))/(((ROUND(Assumptions!$C$5*Assumptions!$C$10,0)*(Assumptions!$C$9*Assumptions!$C$11)+(Assumptions!$C$5-ROUND(Assumptions!$C$5*Assumptions!$C$10,0))*Assumptions!$C$9)*12)+Assumptions!$C$12)

Sheet 20-Year Cash Flow
A2: 20-Year Cash Flow
A3: NOI grows; one fixed mortgage; net cash flow split 60% landowner / 40% NFP
A4: Year | B4: NOI | C4: Debt service | D4: Net cash flow | E4: Landowner 60% | F4: NFP 40% | G4: Mortgage bal.
B5: 1 | C5: =(((((ROUND(Assumptions!$C$5*Assumptions!$C$10,0)*(Assumptions!$C$9*Assumptions!$C$11)+(Assumptions!$C$5-ROUND(Assumptions!$C$5*Assumptions!$C$10,0))*Assumptions!$C$9)*12)+Assumptions!$C$12)*(1-Assumptions!$C$13))-Assumptions!$C$14)*(1+Assumptions!$C$15)^(1-1) | D5: =-(-PMT(Assumptions!$C$18/12,Assumptions!$C$19*12,(Assumptions!$C$17*Assumptions!$C$22))*12) | E5: =C5+D5 | F5: =E5*Assumptions!$C$27 | G5: =E5*Assumptions!$C$28 | H5: =(Assumptions!$C$17*Assumptions!$C$22)*(((1+Assumptions!$C$18/12)^(Assumptions!$C$19*12)-(1+Assumptions!$C$18/12)^(1*12))/((1+Assumptions!$C$18/12)^(Assumptions!$C$19*12)-1))
B6: 2 | C6: =(((((ROUND(Assumptions!$C$5*Assumptions!$C$10,0)*(Assumptions!$C$9*Assumptions!$C$11)+(Assumptions!$C$5-ROUND(Assumptions!$C$5*Assumptions!$C$10,0))*Assumptions!$C$9)*12)+Assumptions!$C$12)*(1-Assumptions!$C$13))-Assumptions!$C$14)*(1+Assumptions!$C$15)^(2-1) | D6: =-(-PMT(Assumptions!$C$18/12,Assumptions!$C$19*12,(Assumptions!$C$17*Assumptions!$C$22))*12) | E6: =C6+D6 | F6: =E6*Assumptions!$C$27 | G6: =E6*Assumptions!$C$28 | H6: =(Assumptions!$C$17*Assumptions!$C$22)*(((1+Assumptions!$C$18/12)^(Assumptions!$C$19*12)-(1+Assumptions!$C$18/12)^(2*12))/((1+Assumptions!$C$18/12)^(Assumptions!$C$19*12)-1))
B7: 3 | C7: =(((((ROUND(Assumptions!$C$5*Assumptions!$C$10,0)*(Assumptions!$C$9*Assumptions!$C$11)+(Assumptions!$C$5-ROUND(Assumptions!$C$5*Assumptions!$C$10,0))*Assumptions!$C$9)*12)+Assumptions!$C$12)*(1-Assumptions!$C$13))-Assumptions!$C$14)*(1+Assumptions!$C$15)^(3-1) | D7: =-(-PMT(Assumptions!$C$18/12,Assumptions!$C$19*12,(Assumptions!$C$17*Assumptions!$C$22))*12) | E7: =C7+D7 | F7: =E7*Assumptions!$C$27 | G7: =E7*Assumptions!$C$28 | H7: =(Assumptions!$C$17*Assumptions!$C$22)*(((1+Assumptions!$C$18/12)^(Assumptions!$C$19*12)-(1+Assumptions!$C$18/12)^(3*12))/((1+Assumptions!$C$18/12)^(Assumptions!$C$19*12)-1))
B8: 4 | C8: =(((((ROUND(Assumptions!$C$5*Assumptions!$C$10,0)*(Assumptions!$C$9*Assumptions!$C$11)+(Assumptions!$C$5-ROUND(Assumptions!$C$5*Assumptions!$C$10,0))*Assumptions!$C$9)*12)+Assumptions!$C$12)*(1-Assumptions!$C$13))-Assumptions!$C$14)*(1+Assumptions!$C$15)^(4-1) | D8: =-(-PMT(Assumptions!$C$18/12,Assumptions!$C$19*12,(Assumptions!$C$17*Assumptions!$C$22))*12) | E8: =C8+D8 | F8: =E8*Assumptions!$C$27 | G8: =E8*Assumptions!$C$28 | H8: =(Assumptions!$C$17*Assumptions!$C$22)*(((1+Assumptions!$C$18/12)^(Assumptions!$C$19*12)-(1+Assumptions!$C$18/12)^(4*12))/((1+Assumptions!$C$18/12)^(Assumptions!$C$19*12)-1))
B9: 5 | C9: =(((((ROUND(Assumptions!$C$5*Assumptions!$C$10,0)*(Assumptions!$C$9*Assumptions!$C$11)+(Assumptions!$C$5-ROUND(Assumptions!$C$5*Assumptions!$C$10,0))*Assumptions!$C$9)*12)+Assumptions!$C$12)*(1-Assumptions!$C$13))-Assumptions!$C$14)*(1+Assumptions!$C$15)^(5-1) | D9: =-(-PMT(Assumptions!$C$18/12,Assumptions!$C$19*12,(Assumptions!$C$17*Assumptions!$C$22))*12) | E9: =C9+D9 | F9: =E9*Assumptions!$C$27 | G9: =E9*Assumptions!$C$28 | H9: =(Assumptions!$C$17*Assumptions!$C$22)*(((1+Assumptions!$C$18/12)^(Assumptions!$C$19*12)-(1+Assumptions!$C$18/12)^(5*12))/((1+Assumptions!$C$18/12)^(Assumptions!$C$19*12)-1))
B10: 6 | C10: =(((((ROUND(Assumptions!$C$5*Assumptions!$C$10,0)*(Assumptions!$C$9*Assumptions!$C$11)+(Assumptions!$C$5-ROUND(Assumptions!$C$5*Assumptions!$C$10,0))*Assumptions!$C$9)*12)+Assumptions!$C$12)*(1-Assumptions!$C$13))-Assumptions!$C$14)*(1+Assumptions!$C$15)^(6-1) | D10: =-(-PMT(Assumptions!$C$18/12,Assumptions!$C$19*12,(Assumptions!$C$17*Assumptions!$C$22))*12) | E10: =C10+D10 | F10: =E10*Assumptions!$C$27 | G10: =E10*Assumptions!$C$28 | H10: =(Assumptions!$C$17*Assumptions!$C$22)*(((1+Assumptions!$C$18/12)^(Assumptions!$C$19*12)-(1+Assumptions!$C$18/12)^(6*12))/((1+Assumptions!$C$18/12)^(Assumptions!$C$19*12)-1))
B11: 7 | C11: =(((((ROUND(Assumptions!$C$5*Assumptions!$C$10,0)*(Assumptions!$C$9*Assumptions!$C$11)+(Assumptions!$C$5-ROUND(Assumptions!$C$5*Assumptions!$C$10,0))*Assumptions!$C$9)*12)+Assumptions!$C$12)*(1-Assumptions!$C$13))-Assumptions!$C$14)*(1+Assumptions!$C$15)^(7-1) | D11: =-(-PMT(Assumptions!$C$18/12,Assumptions!$C$19*12,(Assumptions!$C$17*Assumptions!$C$22))*12) | E11: =C11+D11 | F11: =E11*Assumptions!$C$27 | G11: =E11*Assumptions!$C$28 | H11: =(Assumptions!$C$17*Assumptions!$C$22)*(((1+Assumptions!$C$18/12)^(Assumptions!$C$19*12)-(1+Assumptions!$C$18/12)^(7*12))/((1+Assumptions!$C$18/12)^(Assumptions!$C$19*12)-1))
B12: 8 | C12: =(((((ROUND(Assumptions!$C$5*Assumptions!$C$10,0)*(Assumptions!$C$9*Assumptions!$C$11)+(Assumptions!$C$5-ROUND(Assumptions!$C$5*Assumptions!$C$10,0))*Assumptions!$C$9)*12)+Assumptions!$C$12)*(1-Assumptions!$C$13))-Assumptions!$C$14)*(1+Assumptions!$C$15)^(8-1) | D12: =-(-PMT(Assumptions!$C$18/12,Assumptions!$C$19*12,(Assumptions!$C$17*Assumptions!$C$22))*12) | E12: =C12+D12 | F12: =E12*Assumptions!$C$27 | G12: =E12*Assumptions!$C$28 | H12: =(Assumptions!$C$17*Assumptions!$C$22)*(((1+Assumptions!$C$18/12)^(Assumptions!$C$19*12)-(1+Assumptions!$C$18/12)^(8*12))/((1+Assumptions!$C$18/12)^(Assumptions!$C$19*12)-1))
B13: 9 | C13: =(((((ROUND(Assumptions!$C$5*Assumptions!$C$10,0)*(Assumptions!$C$9*Assumptions!$C$11)+(Assumptions!$C$5-ROUND(Assumptions!$C$5*Assumptions!$C$10,0))*Assumptions!$C$9)*12)+Assumptions!$C$12)*(1-Assumptions!$C$13))-Assumptions!$C$14)*(1+Assumptions!$C$15)^(9-1) | D13: =-(-PMT(Assumptions!$C$18/12,Assumptions!$C$19*12,(Assumptions!$C$17*Assumptions!$C$22))*12) | E13: =C13+D13 | F13: =E13*Assumptions!$C$27 | G13: =E13*Assumptions!$C$28 | H13: =(Assumptions!$C$17*Assumptions!$C$22)*(((1+Assumptions!$C$18/12)^(Assumptions!$C$19*12)-(1+Assumptions!$C$18/12)^(9*12))/((1+Assumptions!$C$18/12)^(Assumptions!$C$19*12)-1))
B14: 10 | C14: =(((((ROUND(Assumptions!$C$5*Assumptions!$C$10,0)*(Assumptions!$C$9*Assumptions!$C$11)+(Assumptions!$C$5-ROUND(Assumptions!$C$5*Assumptions!$C$10,0))*Assumptions!$C$9)*12)+Assumptions!$C$12)*(1-Assumptions!$C$13))-Assumptions!$C$14)*(1+Assumptions!$C$15)^(10-1) | D14: =-(-PMT(Assumptions!$C$18/12,Assumptions!$C$19*12,(Assumptions!$C$17*Assumptions!$C$22))*12) | E14: =C14+D14 | F14: =E14*Assumptions!$C$27 | G14: =E14*Assumptions!$C$28 | H14: =(Assumptions!$C$17*Assumptions!$C$22)*(((1+Assumptions!$C$18/12)^(Assumptions!$C$19*12)-(1+Assumptions!$C$18/12)^(10*12))/((1+Assumptions!$C$18/12)^(Assumptions!$C$19*12)-1))
B15: 11 | C15: =(((((ROUND(Assumptions!$C$5*Assumptions!$C$10,0)*(Assumptions!$C$9*Assumptions!$C$11)+(Assumptions!$C$5-ROUND(Assumptions!$C$5*Assumptions!$C$10,0))*Assumptions!$C$9)*12)+Assumptions!$C$12)*(1-Assumptions!$C$13))-Assumptions!$C$14)*(1+Assumptions!$C$15)^(11-1) | D15: =-(-PMT(Assumptions!$C$18/12,Assumptions!$C$19*12,(Assumptions!$C$17*Assumptions!$C$22))*12) | E15: =C15+D15 | F15: =E15*Assumptions!$C$27 | G15: =E15*Assumptions!$C$28 | H15: =(Assumptions!$C$17*Assumptions!$C$22)*(((1+Assumptions!$C$18/12)^(Assumptions!$C$19*12)-(1+Assumptions!$C$18/12)^(11*12))/((1+Assumptions!$C$18/12)^(Assumptions!$C$19*12)-1))
B16: 12 | C16: =(((((ROUND(Assumptions!$C$5*Assumptions!$C$10,0)*(Assumptions!$C$9*Assumptions!$C$11)+(Assumptions!$C$5-ROUND(Assumptions!$C$5*Assumptions!$C$10,0))*Assumptions!$C$9)*12)+Assumptions!$C$12)*(1-Assumptions!$C$13))-Assumptions!$C$14)*(1+Assumptions!$C$15)^(12-1) | D16: =-(-PMT(Assumptions!$C$18/12,Assumptions!$C$19*12,(Assumptions!$C$17*Assumptions!$C$22))*12) | E16: =C16+D16 | F16: =E16*Assumptions!$C$27 | G16: =E16*Assumptions!$C$28 | H16: =(Assumptions!$C$17*Assumptions!$C$22)*(((1+Assumptions!$C$18/12)^(Assumptions!$C$19*12)-(1+Assumptions!$C$18/12)^(12*12))/((1+Assumptions!$C$18/12)^(Assumptions!$C$19*12)-1))
B17: 13 | C17: =(((((ROUND(Assumptions!$C$5*Assumptions!$C$10,0)*(Assumptions!$C$9*Assumptions!$C$11)+(Assumptions!$C$5-ROUND(Assumptions!$C$5*Assumptions!$C$10,0))*Assumptions!$C$9)*12)+Assumptions!$C$12)*(1-Assumptions!$C$13))-Assumptions!$C$14)*(1+Assumptions!$C$15)^(13-1) | D17: =-(-PMT(Assumptions!$C$18/12,Assumptions!$C$19*12,(Assumptions!$C$17*Assumptions!$C$22))*12) | E17: =C17+D17 | F17: =E17*Assumptions!$C$27 | G17: =E17*Assumptions!$C$28 | H17: =(Assumptions!$C$17*Assumptions!$C$22)*(((1+Assumptions!$C$18/12)^(Assumptions!$C$19*12)-(1+Assumptions!$C$18/12)^(13*12))/((1+Assumptions!$C$18/12)^(Assumptions!$C$19*12)-1))
B18: 14 | C18: =(((((ROUND(Assumptions!$C$5*Assumptions!$C$10,0)*(Assumptions!$C$9*Assumptions!$C$11)+(Assumptions!$C$5-ROUND(Assumptions!$C$5*Assumptions!$C$10,0))*Assumptions!$C$9)*12)+Assumptions!$C$12)*(1-Assumptions!$C$13))-Assumptions!$C$14)*(1+Assumptions!$C$15)^(14-1) | D18: =-(-PMT(Assumptions!$C$18/12,Assumptions!$C$19*12,(Assumptions!$C$17*Assumptions!$C$22))*12) | E18: =C18+D18 | F18: =E18*Assumptions!$C$27 | G18: =E18*Assumptions!$C$28 | H18: =(Assumptions!$C$17*Assumptions!$C$22)*(((1+Assumptions!$C$18/12)^(Assumptions!$C$19*12)-(1+Assumptions!$C$18/12)^(14*12))/((1+Assumptions!$C$18/12)^(Assumptions!$C$19*12)-1))
B19: 15 | C19: =(((((ROUND(Assumptions!$C$5*Assumptions!$C$10,0)*(Assumptions!$C$9*Assumptions!$C$11)+(Assumptions!$C$5-ROUND(Assumptions!$C$5*Assumptions!$C$10,0))*Assumptions!$C$9)*12)+Assumptions!$C$12)*(1-Assumptions!$C$13))-Assumptions!$C$14)*(1+Assumptions!$C$15)^(15-1) | D19: =-(-PMT(Assumptions!$C$18/12,Assumptions!$C$19*12,(Assumptions!$C$17*Assumptions!$C$22))*12) | E19: =C19+D19 | F19: =E19*Assumptions!$C$27 | G19: =E19*Assumptions!$C$28 | H19: =(Assumptions!$C$17*Assumptions!$C$22)*(((1+Assumptions!$C$18/12)^(Assumptions!$C$19*12)-(1+Assumptions!$C$18/12)^(15*12))/((1+Assumptions!$C$18/12)^(Assumptions!$C$19*12)-1))
B20: 16 | C20: =(((((ROUND(Assumptions!$C$5*Assumptions!$C$10,0)*(Assumptions!$C$9*Assumptions!$C$11)+(Assumptions!$C$5-ROUND(Assumptions!$C$5*Assumptions!$C$10,0))*Assumptions!$C$9)*12)+Assumptions!$C$12)*(1-Assumptions!$C$13))-Assumptions!$C$14)*(1+Assumptions!$C$15)^(16-1) | D20: =-(-PMT(Assumptions!$C$18/12,Assumptions!$C$19*12,(Assumptions!$C$17*Assumptions!$C$22))*12) | E20: =C20+D20 | F20: =E20*Assumptions!$C$27 | G20: =E20*Assumptions!$C$28 | H20: =(Assumptions!$C$17*Assumptions!$C$22)*(((1+Assumptions!$C$18/12)^(Assumptions!$C$19*12)-(1+Assumptions!$C$18/12)^(16*12))/((1+Assumptions!$C$18/12)^(Assumptions!$C$19*12)-1))
B21: 17 | C21: =(((((ROUND(Assumptions!$C$5*Assumptions!$C$10,0)*(Assumptions!$C$9*Assumptions!$C$11)+(Assumptions!$C$5-ROUND(Assumptions!$C$5*Assumptions!$C$10,0))*Assumptions!$C$9)*12)+Assumptions!$C$12)*(1-Assumptions!$C$13))-Assumptions!$C$14)*(1+Assumptions!$C$15)^(17-1) | D21: =-(-PMT(Assumptions!$C$18/12,Assumptions!$C$19*12,(Assumptions!$C$17*Assumptions!$C$22))*12) | E21: =C21+D21 | F21: =E21*Assumptions!$C$27 | G21: =E21*Assumptions!$C$28 | H21: =(Assumptions!$C$17*Assumptions!$C$22)*(((1+Assumptions!$C$18/12)^(Assumptions!$C$19*12)-(1+Assumptions!$C$18/12)^(17*12))/((1+Assumptions!$C$18/12)^(Assumptions!$C$19*12)-1))
B22: 18 | C22: =(((((ROUND(Assumptions!$C$5*Assumptions!$C$10,0)*(Assumptions!$C$9*Assumptions!$C$11)+(Assumptions!$C$5-ROUND(Assumptions!$C$5*Assumptions!$C$10,0))*Assumptions!$C$9)*12)+Assumptions!$C$12)*(1-Assumptions!$C$13))-Assumptions!$C$14)*(1+Assumptions!$C$15)^(18-1) | D22: =-(-PMT(Assumptions!$C$18/12,Assumptions!$C$19*12,(Assumptions!$C$17*Assumptions!$C$22))*12) | E22: =C22+D22 | F22: =E22*Assumptions!$C$27 | G22: =E22*Assumptions!$C$28 | H22: =(Assumptions!$C$17*Assumptions!$C$22)*(((1+Assumptions!$C$18/12)^(Assumptions!$C$19*12)-(1+Assumptions!$C$18/12)^(18*12))/((1+Assumptions!$C$18/12)^(Assumptions!$C$19*12)-1))
B23: 19 | C23: =(((((ROUND(Assumptions!$C$5*Assumptions!$C$10,0)*(Assumptions!$C$9*Assumptions!$C$11)+(Assumptions!$C$5-ROUND(Assumptions!$C$5*Assumptions!$C$10,0))*Assumptions!$C$9)*12)+Assumptions!$C$12)*(1-Assumptions!$C$13))-Assumptions!$C$14)*(1+Assumptions!$C$15)^(19-1) | D23: =-(-PMT(Assumptions!$C$18/12,Assumptions!$C$19*12,(Assumptions!$C$17*Assumptions!$C$22))*12) | E23: =C23+D23 | F23: =E23*Assumptions!$C$27 | G23: =E23*Assumptions!$C$28 | H23: =(Assumptions!$C$17*Assumptions!$C$22)*(((1+Assumptions!$C$18/12)^(Assumptions!$C$19*12)-(1+Assumptions!$C$18/12)^(19*12))/((1+Assumptions!$C$18/12)^(Assumptions!$C$19*12)-1))
B24: 20 | C24: =(((((ROUND(Assumptions!$C$5*Assumptions!$C$10,0)*(Assumptions!$C$9*Assumptions!$C$11)+(Assumptions!$C$5-ROUND(Assumptions!$C$5*Assumptions!$C$10,0))*Assumptions!$C$9)*12)+Assumptions!$C$12)*(1-Assumptions!$C$13))-Assumptions!$C$14)*(1+Assumptions!$C$15)^(20-1) | D24: =-(-PMT(Assumptions!$C$18/12,Assumptions!$C$19*12,(Assumptions!$C$17*Assumptions!$C$22))*12) | E24: =C24+D24 | F24: =E24*Assumptions!$C$27 | G24: =E24*Assumptions!$C$28 | H24: =(Assumptions!$C$17*Assumptions!$C$22)*(((1+Assumptions!$C$18/12)^(Assumptions!$C$19*12)-(1+Assumptions!$C$18/12)^(20*12))/((1+Assumptions!$C$18/12)^(Assumptions!$C$19*12)-1))
B25: 20-yr total | E25: =SUM(E5:E24) | F25: =SUM(F5:F24) | G25: =SUM(G5:G24)

Sheet Returns
A2: Returns by Party
A3: Landowner and non-profit outcomes over the 20-year term
A4: LANDOWNER
B5: Day-1 cash draw (60% of land value) | C5: =((Assumptions!$C$6*Assumptions!$C$7)*Assumptions!$C$26)
B6: 20-year income (60% of net cash flow) | C6: ='20-Year Cash Flow'!$F$25
B7: Year-20 payment (retained land + paydown share) | C7: =(((Assumptions!$C$6*Assumptions!$C$7)*(1-Assumptions!$C$26))+Assumptions!$C$27*((Assumptions!$C$17*Assumptions!$C$22)-'20-Year Cash Flow'!$H$24))
B8: Total landowner return | C8: =SUM(C5:C7)
B9: For comparison — sell land today (net of cost) | C9: =(Assumptions!$C$6*Assumptions!$C$7)*(1-Assumptions!$C$29)
B10: Advantage vs. selling | C10: =C8-C9
A12: NON-PROFIT OPERATOR
B13: Building ownership from Day 1 | C13: =0
B14: 20-year income (40% of net cash flow) | C14: ='20-Year Cash Flow'!$G$25
B15: Net equity owned at Year 20 (land+building − debt − land payment) | C15: =(('20-Year Cash Flow'!$C$24/Assumptions!$C$20)-'20-Year Cash Flow'!$H$24-(((Assumptions!$C$6*Assumptions!$C$7)*(1-Assumptions!$C$26))+Assumptions!$C$27*((Assumptions!$C$17*Assumptions!$C$22)-'20-Year Cash Flow'!$H$24)))
B16: Total non-profit value | C16: =C14+C15
B17: + 516 permanently affordable homes (155 at 80% MMR)

Sheet Sensitivity
A2: DSCR Sensitivity
A3: Median market rent × mortgage rate (30% @ 80% MMR, 50-yr amort)
A4: Median market rent | B4: @ 4.00% | C4: @ 4.25% | D4: @ 4.75%
B5: $2,400 | C5: =(((ROUND(Assumptions!$C$5*Assumptions!$C$10,0)*2400*Assumptions!$C$11+(Assumptions!$C$5-ROUND(Assumptions!$C$5*Assumptions!$C$10,0))*2400)*12+Assumptions!$C$12)*(1-Assumptions!$C$13)-Assumptions!$C$14)/(-PMT(0.04/12,Assumptions!$C$19*12,(Assumptions!$C$17*Assumptions!$C$22))*12) | D5: =(((ROUND(Assumptions!$C$5*Assumptions!$C$10,0)*2400*Assumptions!$C$11+(Assumptions!$C$5-ROUND(Assumptions!$C$5*Assumptions!$C$10,0))*2400)*12+Assumptions!$C$12)*(1-Assumptions!$C$13)-Assumptions!$C$14)/(-PMT(0.0425/12,Assumptions!$C$19*12,(Assumptions!$C$17*Assumptions!$C$22))*12) | E5: =(((ROUND(Assumptions!$C$5*Assumptions!$C$10,0)*2400*Assumptions!$C$11+(Assumptions!$C$5-ROUND(Assumptions!$C$5*Assumptions!$C$10,0))*2400)*12+Assumptions!$C$12)*(1-Assumptions!$C$13)-Assumptions!$C$14)/(-PMT(0.0475/12,Assumptions!$C$19*12,(Assumptions!$C$17*Assumptions!$C$22))*12)
B6: $2,500 | C6: =(((ROUND(Assumptions!$C$5*Assumptions!$C$10,0)*2500*Assumptions!$C$11+(Assumptions!$C$5-ROUND(Assumptions!$C$5*Assumptions!$C$10,0))*2500)*12+Assumptions!$C$12)*(1-Assumptions!$C$13)-Assumptions!$C$14)/(-PMT(0.04/12,Assumptions!$C$19*12,(Assumptions!$C$17*Assumptions!$C$22))*12) | D6: =(((ROUND(Assumptions!$C$5*Assumptions!$C$10,0)*2500*Assumptions!$C$11+(Assumptions!$C$5-ROUND(Assumptions!$C$5*Assumptions!$C$10,0))*2500)*12+Assumptions!$C$12)*(1-Assumptions!$C$13)-Assumptions!$C$14)/(-PMT(0.0425/12,Assumptions!$C$19*12,(Assumptions!$C$17*Assumptions!$C$22))*12) | E6: =(((ROUND(Assumptions!$C$5*Assumptions!$C$10,0)*2500*Assumptions!$C$11+(Assumptions!$C$5-ROUND(Assumptions!$C$5*Assumptions!$C$10,0))*2500)*12+Assumptions!$C$12)*(1-Assumptions!$C$13)-Assumptions!$C$14)/(-PMT(0.0475/12,Assumptions!$C$19*12,(Assumptions!$C$17*Assumptions!$C$22))*12)
B7: $2,550 (base) | C7: =(((ROUND(Assumptions!$C$5*Assumptions!$C$10,0)*2550*Assumptions!$C$11+(Assumptions!$C$5-ROUND(Assumptions!$C$5*Assumptions!$C$10,0))*2550)*12+Assumptions!$C$12)*(1-Assumptions!$C$13)-Assumptions!$C$14)/(-PMT(0.04/12,Assumptions!$C$19*12,(Assumptions!$C$17*Assumptions!$C$22))*12) | D7: =(((ROUND(Assumptions!$C$5*Assumptions!$C$10,0)*2550*Assumptions!$C$11+(Assumptions!$C$5-ROUND(Assumptions!$C$5*Assumptions!$C$10,0))*2550)*12+Assumptions!$C$12)*(1-Assumptions!$C$13)-Assumptions!$C$14)/(-PMT(0.0425/12,Assumptions!$C$19*12,(Assumptions!$C$17*Assumptions!$C$22))*12) | E7: =(((ROUND(Assumptions!$C$5*Assumptions!$C$10,0)*2550*Assumptions!$C$11+(Assumptions!$C$5-ROUND(Assumptions!$C$5*Assumptions!$C$10,0))*2550)*12+Assumptions!$C$12)*(1-Assumptions!$C$13)-Assumptions!$C$14)/(-PMT(0.0475/12,Assumptions!$C$19*12,(Assumptions!$C$17*Assumptions!$C$22))*12)
B8: $2,600 | C8: =(((ROUND(Assumptions!$C$5*Assumptions!$C$10,0)*2600*Assumptions!$C$11+(Assumptions!$C$5-ROUND(Assumptions!$C$5*Assumptions!$C$10,0))*2600)*12+Assumptions!$C$12)*(1-Assumptions!$C$13)-Assumptions!$C$14)/(-PMT(0.04/12,Assumptions!$C$19*12,(Assumptions!$C$17*Assumptions!$C$22))*12) | D8: =(((ROUND(Assumptions!$C$5*Assumptions!$C$10,0)*2600*Assumptions!$C$11+(Assumptions!$C$5-ROUND(Assumptions!$C$5*Assumptions!$C$10,0))*2600)*12+Assumptions!$C$12)*(1-Assumptions!$C$13)-Assumptions!$C$14)/(-PMT(0.0425/12,Assumptions!$C$19*12,(Assumptions!$C$17*Assumptions!$C$22))*12) | E8: =(((ROUND(Assumptions!$C$5*Assumptions!$C$10,0)*2600*Assumptions!$C$11+(Assumptions!$C$5-ROUND(Assumptions!$C$5*Assumptions!$C$10,0))*2600)*12+Assumptions!$C$12)*(1-Assumptions!$C$13)-Assumptions!$C$14)/(-PMT(0.0475/12,Assumptions!$C$19*12,(Assumptions!$C$17*Assumptions!$C$22))*12)
B9: $2,700 | C9: =(((ROUND(Assumptions!$C$5*Assumptions!$C$10,0)*2700*Assumptions!$C$11+(Assumptions!$C$5-ROUND(Assumptions!$C$5*Assumptions!$C$10,0))*2700)*12+Assumptions!$C$12)*(1-Assumptions!$C$13)-Assumptions!$C$14)/(-PMT(0.04/12,Assumptions!$C$19*12,(Assumptions!$C$17*Assumptions!$C$22))*12) | D9: =(((ROUND(Assumptions!$C$5*Assumptions!$C$10,0)*2700*Assumptions!$C$11+(Assumptions!$C$5-ROUND(Assumptions!$C$5*Assumptions!$C$10,0))*2700)*12+Assumptions!$C$12)*(1-Assumptions!$C$13)-Assumptions!$C$14)/(-PMT(0.0425/12,Assumptions!$C$19*12,(Assumptions!$C$17*Assumptions!$C$22))*12) | E9: =(((ROUND(Assumptions!$C$5*Assumptions!$C$10,0)*2700*Assumptions!$C$11+(Assumptions!$C$5-ROUND(Assumptions!$C$5*Assumptions!$C$10,0))*2700)*12+Assumptions!$C$12)*(1-Assumptions!$C$13)-Assumptions!$C$14)/(-PMT(0.0475/12,Assumptions!$C$19*12,(Assumptions!$C$17*Assumptions!$C$22))*12)
B11: Red = below the 1.10× CMHC MLI Select coverage floor.

Sheet Notes
A2: Notes & Disclaimer
B4: This workbook is an illustrative development model prepared by Ubuntu Land Trust & Developments for discussion.
B5: Program (516 units, 43 storeys) is from the 28 Athabaska Ave SPA/ZBA architectural set (Delmar Group / ZO1).
B6: Land value, construction costs, rents, operating expenses, cap rate, and financing terms are modelling assumptions
B7: — not a valuation, appraisal, offer, or financial advice. Edit the Assumptions tab; all tabs recalculate.
B8: Affordability: 30% of units (155) held at 80% of median market rent per CMHC MLI Select.
B9: Subject to a quantity-surveyor budget, a verified rent schedule, third-party financing approvals
B10: (CMHC MLI Select, Build Canada Homes, City of Toronto), and definitive legal documentation. Actual results will differ.
